AuDoLab/AuDoLab.py
AuDoLab/__init__.py
AuDoLab/subclasses/__init__.py
AuDoLab/subclasses/abstractscraper.py
AuDoLab/subclasses/abstractscraper_arxiv.py
AuDoLab/subclasses/abstractscraper_pubmed.py
AuDoLab/subclasses/lda.py
AuDoLab/subclasses/one_class_svm.py
AuDoLab/subclasses/preprocessing.py
AuDoLab/subclasses/tf_idf.py
AuDoLab-1.0.16.dist-info/AUTHORS.rst
AuDoLab-1.0.16.dist-info/LICENSE
AuDoLab-1.0.16.dist-info/METADATA
AuDoLab-1.0.16.dist-info/WHEEL
AuDoLab-1.0.16.dist-info/entry_points.txt
AuDoLab-1.0.16.dist-info/top_level.txt
AuDoLab-1.0.16.dist-info/RECORD
