Metadata-Version: 2.1
Name: AuDoLab
Version: 1.0.16
Summary: With AuDoLab you can do LDA on highly imbalanced datasets.
Home-page: https://github.com/ArneTillmann/AuDoLab
Author: Arne Tillmann
Author-email: arne.tillmann.vellmar@gmail.com
License: GNU General Public License v3
Keywords: AuDoLab
Platform: UNKNOWN
Classifier: Development Status :: 2 - Pre-Alpha
Classifier: Intended Audience :: Developers
Classifier: License :: OSI Approved :: GNU General Public License v3 (GPLv3)
Classifier: Natural Language :: English
Classifier: Programming Language :: Python :: 3.8
Requires-Python: >=3.5
License-File: LICENSE
License-File: AUTHORS.rst
Requires-Dist: bump2version (>=0.5.11)
Requires-Dist: wheel (>=0.33.6)
Requires-Dist: watchdog (>=0.9.0)
Requires-Dist: flake8 (>=3.7.8)
Requires-Dist: tox (>=3.14.0)
Requires-Dist: coverage (>=6.0b1)
Requires-Dist: Sphinx (>=3.5.4)
Requires-Dist: twine
Requires-Dist: Click (>=7.0)
Requires-Dist: pytest (>=4.6.5)
Requires-Dist: pytest-runner (>=5.1)
Requires-Dist: numpy (>=1.19.2)
Requires-Dist: pandas (>=1.2.3)
Requires-Dist: webbot (>=0.34)
Requires-Dist: bs4 (>=0.0.1)
Requires-Dist: gensim (>=3.8.3)
Requires-Dist: pyldavis (>=3.3.1)
Requires-Dist: scikit-learn (>=0.24.1)
Requires-Dist: nltk (>=3.5)
Requires-Dist: lime (>=0.2.0.1)
Requires-Dist: matplotlib (>=3.3.4)
Requires-Dist: funcy
Requires-Dist: wordcloud
Requires-Dist: pyppeteer
Requires-Dist: requests (>=2.25.1)
Requires-Dist: tqdm (>=4.62.0)
Requires-Dist: nest-asyncio (>=1.5.1)
Requires-Dist: WordCloud (>=1.8.1)
